paloalto_edl_deduplicator/__init__.py
paloalto_edl_deduplicator/skjhs_ped.py
paloalto_edl_deduplicator-0.1.1.dist-info/LICENSE
paloalto_edl_deduplicator-0.1.1.dist-info/METADATA
paloalto_edl_deduplicator-0.1.1.dist-info/WHEEL
paloalto_edl_deduplicator-0.1.1.dist-info/top_level.txt
paloalto_edl_deduplicator-0.1.1.dist-info/RECORD
