Metadata-Version: 2.1
Name: paloalto-edl-deduplicator
Version: 0.1.1
Summary: A Python package for deduplicating IP addresses and URLs in External Dynamic Lists (EDLs) used with Palo Alto firewalls
Author-email: JHS <llaseine@sk.com>
Project-URL: Homepage, https://www.paloaltonetworks.co.kr
Project-URL: Issues, https://www.paloaltonetworks.co.kr
Classifier: Programming Language :: Python :: 3
Classifier: License :: OSI Approved :: MIT License
Classifier: Operating System :: OS Independent
Requires-Python: >=3.7
License-File: LICENSE
Requires-Dist: schedule
